twilio_thinQLCR/__init__.py
twilio_thinQLCR-2.0.0.dist-info/DESCRIPTION.rst
twilio_thinQLCR-2.0.0.dist-info/METADATA
twilio_thinQLCR-2.0.0.dist-info/RECORD
twilio_thinQLCR-2.0.0.dist-info/WHEEL
twilio_thinQLCR-2.0.0.dist-info/metadata.json
twilio_thinQLCR-2.0.0.dist-info/top_level.txt
