Metadata-Version: 2.0
Name: twilio-thinQLCR
Version: 2.0.0
Summary: Twilio 6.x Wrapper Python Library For thinQ LCR integration.
Home-page: https://github.com/thinqinc/twilio-thinQLCR-python
Author: thinQ
Author-email: info@thinq.com
License: MIT
Keywords: twilio thinq wrapper python
Platform: UNKNOWN
Requires-Dist: twilio (>=6.0)
